CombineMols/CombineMols.py
CombineMols/__init__.py
CombineMols-1.0.1.0.dist-info/LICENSE
CombineMols-1.0.1.0.dist-info/METADATA
CombineMols-1.0.1.0.dist-info/WHEEL
CombineMols-1.0.1.0.dist-info/top_level.txt
CombineMols-1.0.1.0.dist-info/RECORD
