Metadata-Version: 2.1
Name: CombineMols
Version: 1.0.1.0
Summary: Easy to combine two molecules
Home-page: https://github.com/gumgo91
Author: Hyunseung Kong
Author-email: antibody91@naver.com
License: MIT
Platform: UNKNOWN
Classifier: Programming Language :: Python :: 3
Classifier: Programming Language :: Python :: 3.2
Classifier: Programming Language :: Python :: 3.3
Classifier: Programming Language :: Python :: 3.4
Classifier: Programming Language :: Python :: 3.5
Classifier: Programming Language :: Python :: 3.6
Classifier: Programming Language :: Python :: 3.7
Requires-Python: >=3
Requires-Dist: mendeleev
